{"text": "Saul Alvarez enfrento a un Dmitry Bivol en las 175 Libras, rival alto, contundente, de gran fuerza f\u00edsica y mayor alcance.  A veces se gana, a veces se pierde, lo importante es levantarse y seguir adelante.   Respeto para @Canelo  y felicidades @bivol_d   \u00a1Viva M\u00e9xico!   \u270c\ud83c\udffb\ud83c\uddf2\ud83c\uddfd\ud83e\udd81 https://t.co/YsEhf3lmVB", "text_sentiment": 1, "img_sent": {"1": 0, "2": -1}, "img_overall_sent": -1, "overall_sent": -1, "media_url": {"1": "https://pbs.twimg.com/media/FSNn8WYXoAE-Nvd.jpg", "2": "https://pbs.twimg.com/media/FSNn8WZXwAAlZnH.jpg"}}